navio/__init__.py
navio/__main__.py
navio/builder/__init__.py
navio/builder/_nb.py
navio/meta_builder.py
navio_builder_win-1.1.0.dist-info/LICENSE.txt
navio_builder_win-1.1.0.dist-info/METADATA
navio_builder_win-1.1.0.dist-info/WHEEL
navio_builder_win-1.1.0.dist-info/entry_points.txt
navio_builder_win-1.1.0.dist-info/RECORD
