Metadata-Version: 2.1
Name: navio-builder-win
Version: 1.1.0
Summary: navio-builder, without sh dependency, works on windows.
Home-page: https://github.com/matthewdeanmartin/navio-builder/tree/pypi_branch
License: MIT
Keywords: devops,build tool
Author: Matthew Martin
Author-email: matthewdeanmartin@gmail.com
Requires-Python: >=3.8
Classifier: Development Status :: 4 - Beta
Classifier: Environment :: Console
Classifier: Intended Audience :: Developers
Classifier: Intended Audience :: System Administrators
Classifier: License :: OSI Approved :: MIT License
Classifier: Programming Language :: Python :: 3
Classifier: Programming Language :: Python :: 3.8
Classifier: Programming Language :: Python :: 3.9
Classifier: Programming Language :: Python :: 3.10
Classifier: Programming Language :: Python :: 3.11
Classifier: Programming Language :: Python :: 3.12
Classifier: Topic :: Software Development :: Build Tools
Project-URL: Bug Tracker, https://github.com/matthewdeanmartin/navio-builder/tree/pypi_branch
Project-URL: Documentation, https://github.com/matthewdeanmartin/navio-builder/tree/pypi_branch
Project-URL: Repository, https://github.com/matthewdeanmartin/navio-builder/tree/pypi_branch
